{
  "name": "Cards/specialcards/effectCards/7.png",
  "bucket": "egokaisaesultimatetcg.firebasestorage.app",
  "metageneration": 1,
  "generation": 1756480591646,
  "contentType": "image/png",
  "storageClass": "STANDARD",
  "contentDisposition": "inline",
  "downloadTokens": [
    "c2da13da-131c-4082-9476-8fcf752859cf"
  ],
  "etag": "vE9hcevQCdL/oirO7l3cF7mXZ6s",
  "customMetadata": {},
  "timeCreated": "2025-08-29T15:16:31.646Z",
  "updated": "2025-08-29T15:16:31.646Z",
  "size": 1091445,
  "md5Hash": "22MU6nnWKlDaT0E5a7OaTA==",
  "crc32c": "2159470199"
}