{
  "name": "Cards/S/Hiyori.png",
  "bucket": "egokaisaesultimatetcg.firebasestorage.app",
  "metageneration": 1,
  "generation": 1755269398139,
  "contentType": "image/png",
  "storageClass": "STANDARD",
  "contentDisposition": "inline",
  "downloadTokens": [
    "9f0381a5-f04d-4af5-834a-d4a37f3cc847"
  ],
  "etag": "aV+Tyrkpv4/NNJLYazWGjcTv88Q",
  "customMetadata": {},
  "timeCreated": "2025-08-15T14:49:58.139Z",
  "updated": "2025-08-15T14:49:58.139Z",
  "size": 1207024,
  "md5Hash": "BsPSXjBh+ZM64MSRLBVWhA==",
  "crc32c": "622487390"
}